{
  "meta": {
    "application": "Bulls & Bears Fundamentals",
    "source": "Yahoo Finance (yfinance)",
    "last_updated": "2026-07-12T16:16:38.808084+00:00",
    "total_instruments": 83
  },
  "instruments": [
    {
      "symbol": "EURUSD=X",
      "display_name": "Euro / United States Dollar (EUR/USD)",
      "asset_class": "forex_majors",
      "current_spot_pricing": 1.141944,
      "twenty_four_hour_absolute_price_variance": -0.000261,
      "twenty_four_hour_percentage_price_variance": -0.0228,
      "current_institutional_bid_price": 1.141944,
      "current_institutional_ask_price": 1.141292,
      "daily_opening_price": 1.143511,
      "daily_high_price": 1.146395,
      "daily_low_price": 1.141553,
      "previous_session_close": 1.142204,
      "last_updated": "2026-07-12T16:15:57.838036+00:00",
      "calculated_comprehensive_fundamental_bias": "Bullish",
      "final_composite_score": 7.075
    },
    {
      "symbol": "GBPUSD=X",
      "display_name": "British Pound Sterling / United States Dollar (GBP/USD)",
      "asset_class": "forex_majors",
      "current_spot_pricing": 1.340141,
      "twenty_four_hour_absolute_price_variance": -0.00142,
      "twenty_four_hour_percentage_price_variance": -0.1059,
      "current_institutional_bid_price": 1.340141,
      "current_institutional_ask_price": 1.340051,
      "daily_opening_price": 1.340141,
      "daily_high_price": 1.340141,
      "daily_low_price": 1.340141,
      "previous_session_close": 1.341562,
      "last_updated": "2026-07-12T16:15:58.117696+00:00",
      "calculated_comprehensive_fundamental_bias": "Bullish",
      "final_composite_score": 7.075
    },
    {
      "symbol": "USDJPY=X",
      "display_name": "United States Dollar / Japanese Yen (USD/JPY)",
      "asset_class": "forex_majors",
      "current_spot_pricing": 161.671997,
      "twenty_four_hour_absolute_price_variance": -0.867004,
      "twenty_four_hour_percentage_price_variance": -0.5334,
      "current_institutional_bid_price": 161.672,
      "current_institutional_ask_price": 161.728,
      "daily_opening_price": 162.362,
      "daily_high_price": 162.429001,
      "daily_low_price": 161.276001,
      "previous_session_close": 162.539001,
      "last_updated": "2026-07-12T16:15:58.470691+00:00",
      "calculated_comprehensive_fundamental_bias": "Bullish",
      "final_composite_score": 7.075
    },
    {
      "symbol": "AUDUSD=X",
      "display_name": "Australian Dollar / United States Dollar (AUD/USD)",
      "asset_class": "forex_majors",
      "current_spot_pricing": 0.695507,
      "twenty_four_hour_absolute_price_variance": 0.001067,
      "twenty_four_hour_percentage_price_variance": 0.1536,
      "current_institutional_bid_price": 0.695507,
      "current_institutional_ask_price": 0.695024,
      "daily_opening_price": 0.695507,
      "daily_high_price": 0.695507,
      "daily_low_price": 0.695507,
      "previous_session_close": 0.69444,
      "last_updated": "2026-07-12T16:15:58.733612+00:00",
      "calculated_comprehensive_fundamental_bias": "Bullish",
      "final_composite_score": 7.075
    },
    {
      "symbol": "USDCAD=X",
      "display_name": "United States Dollar / Canadian Dollar (USD/CAD)",
      "asset_class": "forex_majors",
      "current_spot_pricing": 1.4153,
      "twenty_four_hour_absolute_price_variance": -0.00094,
      "twenty_four_hour_percentage_price_variance": -0.0664,
      "current_institutional_bid_price": 1.4153,
      "current_institutional_ask_price": 1.416,
      "daily_opening_price": 1.4153,
      "daily_high_price": 1.4153,
      "daily_low_price": 1.4152,
      "previous_session_close": 1.41624,
      "last_updated": "2026-07-12T16:15:59.136891+00:00",
      "calculated_comprehensive_fundamental_bias": "Bullish",
      "final_composite_score": 7.075
    },
    {
      "symbol": "USDCHF=X",
      "display_name": "United States Dollar / Swiss Franc (USD/CHF)",
      "asset_class": "forex_majors",
      "current_spot_pricing": 0.8078,
      "twenty_four_hour_absolute_price_variance": 0.00126,
      "twenty_four_hour_percentage_price_variance": 0.1562,
      "current_institutional_bid_price": 0.8078,
      "current_institutional_ask_price": 0.8094,
      "daily_opening_price": 0.80654,
      "daily_high_price": 0.80894,
      "daily_low_price": 0.803,
      "previous_session_close": 0.80654,
      "last_updated": "2026-07-12T16:15:59.459598+00:00",
      "calculated_comprehensive_fundamental_bias": "Bullish",
      "final_composite_score": 7.075
    },
    {
      "symbol": "NZDUSD=X",
      "display_name": "New Zealand Dollar / United States Dollar (NZD/USD)",
      "asset_class": "forex_majors",
      "current_spot_pricing": 0.576302,
      "twenty_four_hour_absolute_price_variance": 7.3e-05,
      "twenty_four_hour_percentage_price_variance": 0.0127,
      "current_institutional_bid_price": 0.576302,
      "current_institutional_ask_price": 0.575971,
      "daily_opening_price": 0.576302,
      "daily_high_price": 0.576302,
      "daily_low_price": 0.576302,
      "previous_session_close": 0.576229,
      "last_updated": "2026-07-12T16:15:59.754489+00:00",
      "calculated_comprehensive_fundamental_bias": "Bullish",
      "final_composite_score": 7.075
    },
    {
      "symbol": "EURGBP=X",
      "display_name": "Euro / British Pound Sterling (EUR/GBP)",
      "asset_class": "forex_crosses",
      "current_spot_pricing": 0.85167,
      "twenty_four_hour_absolute_price_variance": -0.00082,
      "twenty_four_hour_percentage_price_variance": -0.0962,
      "current_institutional_bid_price": 0.85167,
      "current_institutional_ask_price": 0.85172,
      "daily_opening_price": 0.85262,
      "daily_high_price": 0.85306,
      "daily_low_price": 0.85082,
      "previous_session_close": 0.85249,
      "last_updated": "2026-07-12T16:16:00.014585+00:00",
      "calculated_comprehensive_fundamental_bias": "Bullish",
      "final_composite_score": 7.075
    },
    {
      "symbol": "EURJPY=X",
      "display_name": "Euro / Japanese Yen (EUR/JPY)",
      "asset_class": "forex_crosses",
      "current_spot_pricing": 184.554001,
      "twenty_four_hour_absolute_price_variance": -1.078995,
      "twenty_four_hour_percentage_price_variance": -0.5813,
      "current_institutional_bid_price": 184.554,
      "current_institutional_ask_price": 184.559,
      "daily_opening_price": 185.561996,
      "daily_high_price": 185.673004,
      "daily_low_price": 184.460007,
      "previous_session_close": 185.632996,
      "last_updated": "2026-07-12T16:16:00.294347+00:00",
      "calculated_comprehensive_fundamental_bias": "Bearish",
      "final_composite_score": 3.925
    },
    {
      "symbol": "EURCHF=X",
      "display_name": "Euro / Swiss Franc (EUR/CHF)",
      "asset_class": "forex_crosses",
      "current_spot_pricing": 0.9224,
      "twenty_four_hour_absolute_price_variance": -0.00053,
      "twenty_four_hour_percentage_price_variance": -0.0574,
      "current_institutional_bid_price": 0.9224,
      "current_institutional_ask_price": 0.9234,
      "daily_opening_price": 0.92203,
      "daily_high_price": 0.92324,
      "daily_low_price": 0.91975,
      "previous_session_close": 0.92293,
      "last_updated": "2026-07-12T16:16:00.537473+00:00",
      "calculated_comprehensive_fundamental_bias": "Bullish",
      "final_composite_score": 7.075
    },
    {
      "symbol": "EURNZD=X",
      "display_name": "Euro / New Zealand Dollar (EUR/NZD)",
      "asset_class": "forex_crosses",
      "current_spot_pricing": 1.98049,
      "twenty_four_hour_absolute_price_variance": -0.01701,
      "twenty_four_hour_percentage_price_variance": -0.8516,
      "current_institutional_bid_price": 1.98049,
      "current_institutional_ask_price": 1.98149,
      "daily_opening_price": 1.98501,
      "daily_high_price": 1.98654,
      "daily_low_price": 1.97762,
      "previous_session_close": 1.9975,
      "last_updated": "2026-07-12T16:16:00.984639+00:00",
      "calculated_comprehensive_fundamental_bias": "Bullish",
      "final_composite_score": 7.075
    },
    {
      "symbol": "EURAUD=X",
      "display_name": "Euro / Australian Dollar (EUR/AUD)",
      "asset_class": "forex_crosses",
      "current_spot_pricing": 1.64114,
      "twenty_four_hour_absolute_price_variance": -0.00547,
      "twenty_four_hour_percentage_price_variance": -0.3322,
      "current_institutional_bid_price": 1.64114,
      "current_institutional_ask_price": 1.64214,
      "daily_opening_price": 1.6462,
      "daily_high_price": 1.64854,
      "daily_low_price": 1.64057,
      "previous_session_close": 1.64661,
      "last_updated": "2026-07-12T16:16:01.362084+00:00",
      "calculated_comprehensive_fundamental_bias": "Bullish",
      "final_composite_score": 7.075
    },
    {
      "symbol": "GBPJPY=X",
      "display_name": "British Pound Sterling / Japanese Yen (GBP/JPY)",
      "asset_class": "forex_crosses",
      "current_spot_pricing": 216.688004,
      "twenty_four_hour_absolute_price_variance": -1.00499,
      "twenty_four_hour_percentage_price_variance": -0.4617,
      "current_institutional_bid_price": 216.688,
      "current_institutional_ask_price": 216.698,
      "daily_opening_price": 217.529999,
      "daily_high_price": 217.800003,
      "daily_low_price": 216.453995,
      "previous_session_close": 217.692993,
      "last_updated": "2026-07-12T16:16:01.625500+00:00",
      "calculated_comprehensive_fundamental_bias": "Bearish",
      "final_composite_score": 3.925
    },
    {
      "symbol": "GBPCHF=X",
      "display_name": "British Pound Sterling / Swiss Franc (GBP/CHF)",
      "asset_class": "forex_crosses",
      "current_spot_pricing": 1.0831,
      "twenty_four_hour_absolute_price_variance": 0.00101,
      "twenty_four_hour_percentage_price_variance": 0.0933,
      "current_institutional_bid_price": 1.0831,
      "current_institutional_ask_price": 1.0841,
      "daily_opening_price": 1.08084,
      "daily_high_price": 1.08391,
      "daily_low_price": 1.07969,
      "previous_session_close": 1.08209,
      "last_updated": "2026-07-12T16:16:02.051870+00:00",
      "calculated_comprehensive_fundamental_bias": "Bullish",
      "final_composite_score": 7.075
    },
    {
      "symbol": "GBPAUD=X",
      "display_name": "British Pound Sterling / Australian Dollar (GBP/AUD)",
      "asset_class": "forex_crosses",
      "current_spot_pricing": 1.92839,
      "twenty_four_hour_absolute_price_variance": -0.00342,
      "twenty_four_hour_percentage_price_variance": -0.177,
      "current_institutional_bid_price": 1.92839,
      "current_institutional_ask_price": 1.92849,
      "daily_opening_price": 1.92839,
      "daily_high_price": 1.92839,
      "daily_low_price": 1.92839,
      "previous_session_close": 1.93181,
      "last_updated": "2026-07-12T16:16:02.369860+00:00",
      "calculated_comprehensive_fundamental_bias": "Bullish",
      "final_composite_score": 7.075
    },
    {
      "symbol": "GBPNZD=X",
      "display_name": "British Pound Sterling / New Zealand Dollar (GBP/NZD)",
      "asset_class": "forex_crosses",
      "current_spot_pricing": 2.32658,
      "twenty_four_hour_absolute_price_variance": -0.00108,
      "twenty_four_hour_percentage_price_variance": -0.0464,
      "current_institutional_bid_price": 2.32658,
      "current_institutional_ask_price": 2.32758,
      "daily_opening_price": 2.32658,
      "daily_high_price": 2.32658,
      "daily_low_price": 2.32658,
      "previous_session_close": 2.32766,
      "last_updated": "2026-07-12T16:16:02.772426+00:00",
      "calculated_comprehensive_fundamental_bias": "Bullish",
      "final_composite_score": 7.075
    },
    {
      "symbol": "AUDJPY=X",
      "display_name": "Australian Dollar / Japanese Yen (AUD/JPY)",
      "asset_class": "forex_crosses",
      "current_spot_pricing": 112.417,
      "twenty_four_hour_absolute_price_variance": -0.314003,
      "twenty_four_hour_percentage_price_variance": -0.2785,
      "current_institutional_bid_price": 112.417,
      "current_institutional_ask_price": 112.427,
      "daily_opening_price": 112.658997,
      "daily_high_price": 112.739998,
      "daily_low_price": 112.179001,
      "previous_session_close": 112.731003,
      "last_updated": "2026-07-12T16:16:03.245543+00:00",
      "calculated_comprehensive_fundamental_bias": "Bearish",
      "final_composite_score": 3.925
    },
    {
      "symbol": "AUDCHF=X",
      "display_name": "Australian Dollar / Swiss Franc (AUD/CHF)",
      "asset_class": "forex_crosses",
      "current_spot_pricing": 0.5602,
      "twenty_four_hour_absolute_price_variance": 0.000181,
      "twenty_four_hour_percentage_price_variance": 0.0323,
      "current_institutional_bid_price": 0.5602,
      "current_institutional_ask_price": 0.5627,
      "daily_opening_price": 0.5602,
      "daily_high_price": 0.5602,
      "daily_low_price": 0.5602,
      "previous_session_close": 0.560019,
      "last_updated": "2026-07-12T16:16:05.488314+00:00",
      "calculated_comprehensive_fundamental_bias": "Bullish",
      "final_composite_score": 7.075
    },
    {
      "symbol": "AUDNZD=X",
      "display_name": "Australian Dollar / New Zealand Dollar (AUD/NZD)",
      "asset_class": "forex_crosses",
      "current_spot_pricing": 1.20622,
      "twenty_four_hour_absolute_price_variance": 0.00128,
      "twenty_four_hour_percentage_price_variance": 0.1062,
      "current_institutional_bid_price": 1.20622,
      "current_institutional_ask_price": 1.20722,
      "daily_opening_price": 1.20622,
      "daily_high_price": 1.20622,
      "daily_low_price": 1.20622,
      "previous_session_close": 1.20494,
      "last_updated": "2026-07-12T16:16:05.828725+00:00",
      "calculated_comprehensive_fundamental_bias": "Bullish",
      "final_composite_score": 7.075
    },
    {
      "symbol": "CADJPY=X",
      "display_name": "Canadian Dollar / Japanese Yen (CAD/JPY)",
      "asset_class": "forex_crosses",
      "current_spot_pricing": 114.213997,
      "twenty_four_hour_absolute_price_variance": -0.506004,
      "twenty_four_hour_percentage_price_variance": -0.4411,
      "current_institutional_bid_price": 114.214,
      "current_institutional_ask_price": 114.264,
      "daily_opening_price": 114.549004,
      "daily_high_price": 114.633003,
      "daily_low_price": 113.982002,
      "previous_session_close": 114.720001,
      "last_updated": "2026-07-12T16:16:06.195164+00:00",
      "calculated_comprehensive_fundamental_bias": "Bearish",
      "final_composite_score": 3.925
    },
    {
      "symbol": "CHFJPY=X",
      "display_name": "Swiss Franc / Japanese Yen (CHF/JPY)",
      "asset_class": "forex_crosses",
      "current_spot_pricing": 199.973007,
      "twenty_four_hour_absolute_price_variance": -1.140656,
      "twenty_four_hour_percentage_price_variance": -0.5672,
      "current_institutional_bid_price": 199.973,
      "current_institutional_ask_price": 199.978,
      "daily_opening_price": 201.220993,
      "daily_high_price": 201.326004,
      "daily_low_price": 199.912994,
      "previous_session_close": 201.113663,
      "last_updated": "2026-07-12T16:16:06.475670+00:00",
      "calculated_comprehensive_fundamental_bias": "Bearish",
      "final_composite_score": 3.925
    },
    {
      "symbol": "NZDJPY=X",
      "display_name": "New Zealand Dollar / Japanese Yen (NZD/JPY)",
      "asset_class": "forex_crosses",
      "current_spot_pricing": 93.157997,
      "twenty_four_hour_absolute_price_variance": 0.285995,
      "twenty_four_hour_percentage_price_variance": 0.3079,
      "current_institutional_bid_price": 93.158,
      "current_institutional_ask_price": 93.168,
      "daily_opening_price": 93.402,
      "daily_high_price": 93.571999,
      "daily_low_price": 93.089996,
      "previous_session_close": 92.872002,
      "last_updated": "2026-07-12T16:16:06.865669+00:00",
      "calculated_comprehensive_fundamental_bias": "Bearish",
      "final_composite_score": 3.925
    },
    {
      "symbol": "EURNOK=X",
      "display_name": "Euro / Norwegian Krone (EUR/NOK)",
      "asset_class": "forex_crosses",
      "current_spot_pricing": 11.16298,
      "twenty_four_hour_absolute_price_variance": 0.01649,
      "twenty_four_hour_percentage_price_variance": 0.1479,
      "current_institutional_bid_price": 11.16298,
      "current_institutional_ask_price": 11.16798,
      "daily_opening_price": 11.10987,
      "daily_high_price": 11.1716,
      "daily_low_price": 11.09017,
      "previous_session_close": 11.14649,
      "last_updated": "2026-07-12T16:16:07.082794+00:00",
      "calculated_comprehensive_fundamental_bias": "Bullish",
      "final_composite_score": 7.075
    },
    {
      "symbol": "EURSEK=X",
      "display_name": "Euro / Swedish Krona (EUR/SEK)",
      "asset_class": "forex_crosses",
      "current_spot_pricing": 11.02775,
      "twenty_four_hour_absolute_price_variance": -0.04084,
      "twenty_four_hour_percentage_price_variance": -0.369,
      "current_institutional_bid_price": 11.02775,
      "current_institutional_ask_price": 11.03275,
      "daily_opening_price": 11.04676,
      "daily_high_price": 11.0505,
      "daily_low_price": 11.00469,
      "previous_session_close": 11.06859,
      "last_updated": "2026-07-12T16:16:07.456302+00:00",
      "calculated_comprehensive_fundamental_bias": "Bullish",
      "final_composite_score": 7.075
    },
    {
      "symbol": "USDNOK=X",
      "display_name": "United States Dollar / Norwegian Krone (USD/NOK)",
      "asset_class": "forex_crosses",
      "current_spot_pricing": 9.7703,
      "twenty_four_hour_absolute_price_variance": 0.05828,
      "twenty_four_hour_percentage_price_variance": 0.6001,
      "current_institutional_bid_price": 9.7703,
      "current_institutional_ask_price": 9.7951,
      "daily_opening_price": 9.7703,
      "daily_high_price": 9.7703,
      "daily_low_price": 9.7703,
      "previous_session_close": 9.71202,
      "last_updated": "2026-07-12T16:16:07.742837+00:00",
      "calculated_comprehensive_fundamental_bias": "Bullish",
      "final_composite_score": 5.325
    },
    {
      "symbol": "USDSEK=X",
      "display_name": "United States Dollar / Swedish Krona (USD/SEK)",
      "asset_class": "forex_crosses",
      "current_spot_pricing": 9.65892,
      "twenty_four_hour_absolute_price_variance": -0.03132,
      "twenty_four_hour_percentage_price_variance": -0.3232,
      "current_institutional_bid_price": 9.65892,
      "current_institutional_ask_price": 9.66951,
      "daily_opening_price": 9.6498,
      "daily_high_price": 9.6498,
      "daily_low_price": 9.6498,
      "previous_session_close": 9.69024,
      "last_updated": "2026-07-12T16:16:08.072342+00:00",
      "calculated_comprehensive_fundamental_bias": "Bullish",
      "final_composite_score": 5.325
    },
    {
      "symbol": "USDSGD=X",
      "display_name": "United States Dollar / Singapore Dollar (USD/SGD)",
      "asset_class": "forex_crosses",
      "current_spot_pricing": 1.2914,
      "twenty_four_hour_absolute_price_variance": -0.0006,
      "twenty_four_hour_percentage_price_variance": -0.0464,
      "current_institutional_bid_price": 1.2914,
      "current_institutional_ask_price": 1.2921,
      "daily_opening_price": 1.2914,
      "daily_high_price": 1.2914,
      "daily_low_price": 1.2914,
      "previous_session_close": 1.292,
      "last_updated": "2026-07-12T16:16:08.453490+00:00",
      "calculated_comprehensive_fundamental_bias": "Bullish",
      "final_composite_score": 5.325
    },
    {
      "symbol": "USDHKD=X",
      "display_name": "United States Dollar / Hong Kong Dollar (USD/HKD)",
      "asset_class": "forex_crosses",
      "current_spot_pricing": 7.8396,
      "twenty_four_hour_absolute_price_variance": 0.0038,
      "twenty_four_hour_percentage_price_variance": 0.0485,
      "current_institutional_bid_price": 7.8396,
      "current_institutional_ask_price": 7.8398,
      "daily_opening_price": 7.8396,
      "daily_high_price": 7.8396,
      "daily_low_price": 7.8393,
      "previous_session_close": 7.8358,
      "last_updated": "2026-07-12T16:16:10.777485+00:00",
      "calculated_comprehensive_fundamental_bias": "Bullish",
      "final_composite_score": 5.325
    },
    {
      "symbol": "USDKRW=X",
      "display_name": "United States Dollar / South Korean Won (USD/KRW)",
      "asset_class": "forex_crosses",
      "current_spot_pricing": 1498.869995,
      "twenty_four_hour_absolute_price_variance": -7.040039,
      "twenty_four_hour_percentage_price_variance": -0.4675,
      "current_institutional_bid_price": 1498.87,
      "current_institutional_ask_price": 1499.87,
      "daily_opening_price": 1498.869995,
      "daily_high_price": 1498.869995,
      "daily_low_price": 1498.869995,
      "previous_session_close": 1505.910034,
      "last_updated": "2026-07-12T16:16:11.018057+00:00",
      "calculated_comprehensive_fundamental_bias": "Bullish",
      "final_composite_score": 5.325
    },
    {
      "symbol": "USDTWD=X",
      "display_name": "United States Dollar / Taiwan Dollar (USD/TWD)",
      "asset_class": "forex_crosses",
      "current_spot_pricing": 32.098999,
      "twenty_four_hour_absolute_price_variance": 0.001801,
      "twenty_four_hour_percentage_price_variance": 0.0056,
      "current_institutional_bid_price": 32.099,
      "current_institutional_ask_price": 32.199,
      "daily_opening_price": 32.098999,
      "daily_high_price": 32.098999,
      "daily_low_price": 32.098999,
      "previous_session_close": 32.097198,
      "last_updated": "2026-07-12T16:16:11.335484+00:00",
      "calculated_comprehensive_fundamental_bias": "Bullish",
      "final_composite_score": 5.325
    },
    {
      "symbol": "USDINR=X",
      "display_name": "United States Dollar / Indian Rupee (USD/INR)",
      "asset_class": "forex_crosses",
      "current_spot_pricing": 95.370003,
      "twenty_four_hour_absolute_price_variance": -0.020195,
      "twenty_four_hour_percentage_price_variance": -0.0212,
      "current_institutional_bid_price": 95.37,
      "current_institutional_ask_price": 95.42,
      "daily_opening_price": 95.370003,
      "daily_high_price": 95.370003,
      "daily_low_price": 95.370003,
      "previous_session_close": 95.390198,
      "last_updated": "2026-07-12T16:16:11.601472+00:00",
      "calculated_comprehensive_fundamental_bias": "Bullish",
      "final_composite_score": 5.325
    },
    {
      "symbol": "USDBRL=X",
      "display_name": "United States Dollar / Brazilian Real (USD/BRL)",
      "asset_class": "forex_crosses",
      "current_spot_pricing": 5.1075,
      "twenty_four_hour_absolute_price_variance": -0.056,
      "twenty_four_hour_percentage_price_variance": -1.0845,
      "current_institutional_bid_price": 5.1075,
      "current_institutional_ask_price": 5.11,
      "daily_opening_price": 5.1186,
      "daily_high_price": 5.1269,
      "daily_low_price": 5.0982,
      "previous_session_close": 5.1635,
      "last_updated": "2026-07-12T16:16:11.896158+00:00",
      "calculated_comprehensive_fundamental_bias": "Bullish",
      "final_composite_score": 5.325
    },
    {
      "symbol": "USDMXN=X",
      "display_name": "United States Dollar / Mexican Peso (USD/MXN)",
      "asset_class": "forex_crosses",
      "current_spot_pricing": 17.462,
      "twenty_four_hour_absolute_price_variance": -0.0762,
      "twenty_four_hour_percentage_price_variance": -0.4345,
      "current_institutional_bid_price": 17.462,
      "current_institutional_ask_price": 17.492,
      "daily_opening_price": 17.462,
      "daily_high_price": 17.462,
      "daily_low_price": 17.462,
      "previous_session_close": 17.5382,
      "last_updated": "2026-07-12T16:16:12.385576+00:00",
      "calculated_comprehensive_fundamental_bias": "Bullish",
      "final_composite_score": 5.325
    },
    {
      "symbol": "USDZAR=X",
      "display_name": "United States Dollar / South African Rand (USD/ZAR)",
      "asset_class": "forex_crosses",
      "current_spot_pricing": 16.346701,
      "twenty_four_hour_absolute_price_variance": 0.0317,
      "twenty_four_hour_percentage_price_variance": 0.1943,
      "current_institutional_bid_price": 16.3467,
      "current_institutional_ask_price": 16.3767,
      "daily_opening_price": 16.346701,
      "daily_high_price": 16.346701,
      "daily_low_price": 16.346201,
      "previous_session_close": 16.315001,
      "last_updated": "2026-07-12T16:16:12.801183+00:00",
      "calculated_comprehensive_fundamental_bias": "Bullish",
      "final_composite_score": 5.325
    },
    {
      "symbol": "USDTRY=X",
      "display_name": "United States Dollar / Turkish Lira (USD/TRY)",
      "asset_class": "forex_crosses",
      "current_spot_pricing": 46.9627,
      "twenty_four_hour_absolute_price_variance": 0.014999,
      "twenty_four_hour_percentage_price_variance": 0.0319,
      "current_institutional_bid_price": 46.9627,
      "current_institutional_ask_price": 46.969,
      "daily_opening_price": 46.9627,
      "daily_high_price": 46.9627,
      "daily_low_price": 46.9627,
      "previous_session_close": 46.947701,
      "last_updated": "2026-07-12T16:16:13.151888+00:00",
      "calculated_comprehensive_fundamental_bias": "Bullish",
      "final_composite_score": 5.325
    },
    {
      "symbol": "USDPLN=X",
      "display_name": "United States Dollar / Polish Zloty (USD/PLN)",
      "asset_class": "forex_crosses",
      "current_spot_pricing": 3.7851,
      "twenty_four_hour_absolute_price_variance": -0.00023,
      "twenty_four_hour_percentage_price_variance": -0.0061,
      "current_institutional_bid_price": 3.7851,
      "current_institutional_ask_price": 3.7891,
      "daily_opening_price": 3.7851,
      "daily_high_price": 3.7851,
      "daily_low_price": 3.7851,
      "previous_session_close": 3.78533,
      "last_updated": "2026-07-12T16:16:13.451535+00:00",
      "calculated_comprehensive_fundamental_bias": "Bullish",
      "final_composite_score": 5.325
    },
    {
      "symbol": "^DJI",
      "display_name": "Industrial Average Dow Jones 30 Index (^DJI)",
      "asset_class": "global_indices",
      "current_spot_pricing": 52637.011719,
      "twenty_four_hour_absolute_price_variance": 149.601562,
      "twenty_four_hour_percentage_price_variance": 0.285,
      "current_institutional_bid_price": 52537.39,
      "current_institutional_ask_price": 52765.39,
      "daily_opening_price": 52622.921875,
      "daily_high_price": 52709.75,
      "daily_low_price": 52266.808594,
      "previous_session_close": 52487.410156,
      "last_updated": "2026-07-12T16:16:13.749369+00:00",
      "calculated_comprehensive_fundamental_bias": "Bullish",
      "final_composite_score": 5.925
    },
    {
      "symbol": "^GSPC",
      "display_name": "Standard & Poor's 500 Index (^GSPC)",
      "asset_class": "global_indices",
      "current_spot_pricing": 7575.390137,
      "twenty_four_hour_absolute_price_variance": 31.75,
      "twenty_four_hour_percentage_price_variance": 0.4209,
      "current_institutional_bid_price": 7540.17,
      "current_institutional_ask_price": 7599.22,
      "daily_opening_price": 7547.640137,
      "daily_high_price": 7579.930176,
      "daily_low_price": 7508.160156,
      "previous_session_close": 7543.640137,
      "last_updated": "2026-07-12T16:16:14.023592+00:00",
      "calculated_comprehensive_fundamental_bias": "Bullish",
      "final_composite_score": 5.925
    },
    {
      "symbol": "^IXIC",
      "display_name": "NASDAQ Composite 100 Index (^IXIC)",
      "asset_class": "global_indices",
      "current_spot_pricing": 26281.609375,
      "twenty_four_hour_absolute_price_variance": 74.71875,
      "twenty_four_hour_percentage_price_variance": 0.2851,
      "current_institutional_bid_price": 0.0,
      "current_institutional_ask_price": 0.0,
      "daily_opening_price": 26175.539062,
      "daily_high_price": 26301.539062,
      "daily_low_price": 26009.490234,
      "previous_session_close": 26206.890625,
      "last_updated": "2026-07-12T16:16:14.227230+00:00",
      "calculated_comprehensive_fundamental_bias": "Bullish",
      "final_composite_score": 5.925
    },
    {
      "symbol": "^RUT",
      "display_name": "Russell 2000 Small-Cap Index (^RUT)",
      "asset_class": "global_indices",
      "current_spot_pricing": 2977.810059,
      "twenty_four_hour_absolute_price_variance": -14.72998,
      "twenty_four_hour_percentage_price_variance": -0.4922,
      "current_institutional_bid_price": 0.0,
      "current_institutional_ask_price": 0.0,
      "daily_opening_price": 2996.110107,
      "daily_high_price": 2998.179932,
      "daily_low_price": 2963.159912,
      "previous_session_close": 2992.540039,
      "last_updated": "2026-07-12T16:16:14.487736+00:00",
      "calculated_comprehensive_fundamental_bias": "Bullish",
      "final_composite_score": 5.925
    },
    {
      "symbol": "^VIX",
      "display_name": "CBOE Volatility Index (^VIX)",
      "asset_class": "global_indices",
      "current_spot_pricing": 15.03,
      "twenty_four_hour_absolute_price_variance": -0.81,
      "twenty_four_hour_percentage_price_variance": -5.1136,
      "current_institutional_bid_price": 0.0,
      "current_institutional_ask_price": 0.0,
      "daily_opening_price": 16.059999,
      "daily_high_price": 16.16,
      "daily_low_price": 14.96,
      "previous_session_close": 15.84,
      "last_updated": "2026-07-12T16:16:14.771732+00:00",
      "calculated_comprehensive_fundamental_bias": "Bullish",
      "final_composite_score": 5.925
    },
    {
      "symbol": "^FTSE",
      "display_name": "Financial Times Stock Exchange 100 Index (^FTSE)",
      "asset_class": "global_indices",
      "current_spot_pricing": 10497.299805,
      "twenty_four_hour_absolute_price_variance": 24.799805,
      "twenty_four_hour_percentage_price_variance": 0.2368,
      "current_institutional_bid_price": 0.0,
      "current_institutional_ask_price": 0.0,
      "daily_opening_price": 10471.900391,
      "daily_high_price": 10513.900391,
      "daily_low_price": 10462.799805,
      "previous_session_close": 10472.5,
      "last_updated": "2026-07-12T16:16:15.071275+00:00",
      "calculated_comprehensive_fundamental_bias": "Bullish",
      "final_composite_score": 5.925
    },
    {
      "symbol": "^N225",
      "display_name": "Nikkei 225 Stock Average Index (^N225)",
      "asset_class": "global_indices",
      "current_spot_pricing": 68557.726562,
      "twenty_four_hour_absolute_price_variance": 813.875,
      "twenty_four_hour_percentage_price_variance": 1.2014,
      "current_institutional_bid_price": 0.0,
      "current_institutional_ask_price": 0.0,
      "daily_opening_price": 68526.71875,
      "daily_high_price": 69374.859375,
      "daily_low_price": 68271.90625,
      "previous_session_close": 67743.851562,
      "last_updated": "2026-07-12T16:16:15.347275+00:00",
      "calculated_comprehensive_fundamental_bias": "Bullish",
      "final_composite_score": 5.925
    },
    {
      "symbol": "^AXJO",
      "display_name": "S&P/ASX 200 Australian Index (^AXJO)",
      "asset_class": "global_indices",
      "current_spot_pricing": 8806.0,
      "twenty_four_hour_absolute_price_variance": 43.5,
      "twenty_four_hour_percentage_price_variance": 0.4964,
      "current_institutional_bid_price": 0.0,
      "current_institutional_ask_price": 0.0,
      "daily_opening_price": 8762.5,
      "daily_high_price": 8821.599609,
      "daily_low_price": 8748.599609,
      "previous_session_close": 8762.5,
      "last_updated": "2026-07-12T16:16:15.617543+00:00",
      "calculated_comprehensive_fundamental_bias": "Bullish",
      "final_composite_score": 5.925
    },
    {
      "symbol": "^HSI",
      "display_name": "Hang Seng Hong Kong Index (^HSI)",
      "asset_class": "global_indices",
      "current_spot_pricing": 24175.119141,
      "twenty_four_hour_absolute_price_variance": 144.939453,
      "twenty_four_hour_percentage_price_variance": 0.6032,
      "current_institutional_bid_price": 0.0,
      "current_institutional_ask_price": 0.0,
      "daily_opening_price": 24213.439453,
      "daily_high_price": 24499.630859,
      "daily_low_price": 24064.619141,
      "previous_session_close": 24030.179688,
      "last_updated": "2026-07-12T16:16:16.092734+00:00",
      "calculated_comprehensive_fundamental_bias": "Bullish",
      "final_composite_score": 5.925
    },
    {
      "symbol": "^STOXX50E",
      "display_name": "EURO STOXX 50 Index (^STOXX50E)",
      "asset_class": "global_indices",
      "current_spot_pricing": 6269.970215,
      "twenty_four_hour_absolute_price_variance": -14.299805,
      "twenty_four_hour_percentage_price_variance": -0.2275,
      "current_institutional_bid_price": 0.0,
      "current_institutional_ask_price": 0.0,
      "daily_opening_price": 6266.830078,
      "daily_high_price": 6287.709961,
      "daily_low_price": 6242.350098,
      "previous_session_close": 6284.27002,
      "last_updated": "2026-07-12T16:16:16.355185+00:00",
      "calculated_comprehensive_fundamental_bias": "Bullish",
      "final_composite_score": 5.925
    },
    {
      "symbol": "^FCHI",
      "display_name": "CAC 40 French Index (^FCHI)",
      "asset_class": "global_indices",
      "current_spot_pricing": 8338.969727,
      "twenty_four_hour_absolute_price_variance": 12.349609,
      "twenty_four_hour_percentage_price_variance": 0.1483,
      "current_institutional_bid_price": 0.0,
      "current_institutional_ask_price": 0.0,
      "daily_opening_price": 8324.070312,
      "daily_high_price": 8350.830078,
      "daily_low_price": 8284.240234,
      "previous_session_close": 8326.620117,
      "last_updated": "2026-07-12T16:16:18.691077+00:00",
      "calculated_comprehensive_fundamental_bias": "Bullish",
      "final_composite_score": 5.925
    },
    {
      "symbol": "^GDAXI",
      "display_name": "DAX 30 German Index (^GDAXI)",
      "asset_class": "global_indices",
      "current_spot_pricing": 25067.089844,
      "twenty_four_hour_absolute_price_variance": -51.179688,
      "twenty_four_hour_percentage_price_variance": -0.2038,
      "current_institutional_bid_price": 0.0,
      "current_institutional_ask_price": 0.0,
      "daily_opening_price": 25081.189453,
      "daily_high_price": 25195.830078,
      "daily_low_price": 24937.519531,
      "previous_session_close": 25118.269531,
      "last_updated": "2026-07-12T16:16:19.016227+00:00",
      "calculated_comprehensive_fundamental_bias": "Bullish",
      "final_composite_score": 5.925
    },
    {
      "symbol": "^BSESN",
      "display_name": "BSE SENSEX Indian Index (^BSESN)",
      "asset_class": "global_indices",
      "current_spot_pricing": 77569.390625,
      "twenty_four_hour_absolute_price_variance": 827.570312,
      "twenty_four_hour_percentage_price_variance": 1.0784,
      "current_institutional_bid_price": 0.0,
      "current_institutional_ask_price": 0.0,
      "daily_opening_price": 77395.632812,
      "daily_high_price": 77642.226562,
      "daily_low_price": 77320.5625,
      "previous_session_close": 76741.820312,
      "last_updated": "2026-07-12T16:16:19.403786+00:00",
      "calculated_comprehensive_fundamental_bias": "Bullish",
      "final_composite_score": 5.925
    },
    {
      "symbol": "^NSEI",
      "display_name": "NIFTY 50 Indian Index (^NSEI)",
      "asset_class": "global_indices",
      "current_spot_pricing": 24206.900391,
      "twenty_four_hour_absolute_price_variance": 244.099609,
      "twenty_four_hour_percentage_price_variance": 1.0187,
      "current_institutional_bid_price": 0.0,
      "current_institutional_ask_price": 0.0,
      "daily_opening_price": 24124.699219,
      "daily_high_price": 24228.449219,
      "daily_low_price": 24120.349609,
      "previous_session_close": 23962.800781,
      "last_updated": "2026-07-12T16:16:19.729705+00:00",
      "calculated_comprehensive_fundamental_bias": "Bullish",
      "final_composite_score": 5.925
    },
    {
      "symbol": "^KS11",
      "display_name": "KOSPI South Korean Index (^KS11)",
      "asset_class": "global_indices",
      "current_spot_pricing": 7475.939941,
      "twenty_four_hour_absolute_price_variance": 184.029785,
      "twenty_four_hour_percentage_price_variance": 2.5238,
      "current_institutional_bid_price": 0.0,
      "current_institutional_ask_price": 0.0,
      "daily_opening_price": 7552.490234,
      "daily_high_price": 7704.930176,
      "daily_low_price": 7429.509766,
      "previous_session_close": 7291.910156,
      "last_updated": "2026-07-12T16:16:20.602925+00:00",
      "calculated_comprehensive_fundamental_bias": "Bullish",
      "final_composite_score": 5.925
    },
    {
      "symbol": "^TWII",
      "display_name": "TSEC Weighted Taiwan Index (^TWII)",
      "asset_class": "global_indices",
      "current_spot_pricing": 45354.609375,
      "twenty_four_hour_absolute_price_variance": 0.0,
      "twenty_four_hour_percentage_price_variance": 0.0,
      "current_institutional_bid_price": 0.0,
      "current_institutional_ask_price": 0.0,
      "daily_opening_price": 45805.621094,
      "daily_high_price": 46064.058594,
      "daily_low_price": 45352.410156,
      "previous_session_close": 45354.609375,
      "last_updated": "2026-07-12T16:16:20.900075+00:00",
      "calculated_comprehensive_fundamental_bias": "Bullish",
      "final_composite_score": 5.925
    },
    {
      "symbol": "^BVSP",
      "display_name": "IBOVESPA Brazilian Index (^BVSP)",
      "asset_class": "global_indices",
      "current_spot_pricing": 177866.0,
      "twenty_four_hour_absolute_price_variance": 5124.0,
      "twenty_four_hour_percentage_price_variance": 2.9663,
      "current_institutional_bid_price": 0.0,
      "current_institutional_ask_price": 0.0,
      "daily_opening_price": 172761.0,
      "daily_high_price": 177866.0,
      "daily_low_price": 172761.0,
      "previous_session_close": 172742.0,
      "last_updated": "2026-07-12T16:16:21.227073+00:00",
      "calculated_comprehensive_fundamental_bias": "Bullish",
      "final_composite_score": 5.925
    },
    {
      "symbol": "^MXX",
      "display_name": "IPC Mexican Index (^MXX)",
      "asset_class": "global_indices",
      "current_spot_pricing": 66496.101562,
      "twenty_four_hour_absolute_price_variance": 388.820312,
      "twenty_four_hour_percentage_price_variance": 0.5882,
      "current_institutional_bid_price": 0.0,
      "current_institutional_ask_price": 0.0,
      "daily_opening_price": 66140.53125,
      "daily_high_price": 66798.046875,
      "daily_low_price": 66140.53125,
      "previous_session_close": 66107.28125,
      "last_updated": "2026-07-12T16:16:21.557634+00:00",
      "calculated_comprehensive_fundamental_bias": "Bullish",
      "final_composite_score": 5.925
    },
    {
      "symbol": "^IPSA",
      "display_name": "IPSA Chilean Index (^IPSA)",
      "asset_class": "global_indices",
      "current_spot_pricing": 11056.870117,
      "twenty_four_hour_absolute_price_variance": 0.0,
      "twenty_four_hour_percentage_price_variance": 0.0,
      "current_institutional_bid_price": 0.0,
      "current_institutional_ask_price": 0.0,
      "daily_opening_price": 11025.290039,
      "daily_high_price": 11062.780273,
      "daily_low_price": 10960.700195,
      "previous_session_close": 11056.870117,
      "last_updated": "2026-07-12T16:16:21.911056+00:00",
      "calculated_comprehensive_fundamental_bias": "Bullish",
      "final_composite_score": 5.925
    },
    {
      "symbol": "GC=F",
      "display_name": "Gold Futures (GC=F)",
      "asset_class": "commodities",
      "current_spot_pricing": 4113.700195,
      "twenty_four_hour_absolute_price_variance": 0.0,
      "twenty_four_hour_percentage_price_variance": 0.0,
      "current_institutional_bid_price": 4125.1,
      "current_institutional_ask_price": 4131.0,
      "daily_opening_price": 4135.399902,
      "daily_high_price": 4144.600098,
      "daily_low_price": 4081.699951,
      "previous_session_close": 4113.700195,
      "last_updated": "2026-07-12T16:16:24.719521+00:00",
      "calculated_comprehensive_fundamental_bias": "Bullish",
      "final_composite_score": 5.375
    },
    {
      "symbol": "SI=F",
      "display_name": "Silver Futures (SI=F)",
      "asset_class": "commodities",
      "current_spot_pricing": 60.165001,
      "twenty_four_hour_absolute_price_variance": 0.0,
      "twenty_four_hour_percentage_price_variance": 0.0,
      "current_institutional_bid_price": 60.2,
      "current_institutional_ask_price": 60.5,
      "daily_opening_price": 60.415001,
      "daily_high_price": 61.195,
      "daily_low_price": 59.244999,
      "previous_session_close": 60.165001,
      "last_updated": "2026-07-12T16:16:24.984315+00:00",
      "calculated_comprehensive_fundamental_bias": "Bullish",
      "final_composite_score": 5.375
    },
    {
      "symbol": "CL=F",
      "display_name": "Crude Oil West Texas Intermediate Futures (CL=F)",
      "asset_class": "commodities",
      "current_spot_pricing": 71.410004,
      "twenty_four_hour_absolute_price_variance": 0.0,
      "twenty_four_hour_percentage_price_variance": 0.0,
      "current_institutional_bid_price": 71.44,
      "current_institutional_ask_price": 71.57,
      "daily_opening_price": 71.860001,
      "daily_high_price": 73.160004,
      "daily_low_price": 70.769997,
      "previous_session_close": 71.410004,
      "last_updated": "2026-07-12T16:16:25.496241+00:00",
      "calculated_comprehensive_fundamental_bias": "Bullish",
      "final_composite_score": 5.375
    },
    {
      "symbol": "BZ=F",
      "display_name": "Brent Crude Oil Futures (BZ=F)",
      "asset_class": "commodities",
      "current_spot_pricing": 76.010002,
      "twenty_four_hour_absolute_price_variance": 0.0,
      "twenty_four_hour_percentage_price_variance": 0.0,
      "current_institutional_bid_price": 75.34,
      "current_institutional_ask_price": 77.27,
      "daily_opening_price": 75.970001,
      "daily_high_price": 77.559998,
      "daily_low_price": 75.309998,
      "previous_session_close": 76.010002,
      "last_updated": "2026-07-12T16:16:25.842561+00:00",
      "calculated_comprehensive_fundamental_bias": "Bullish",
      "final_composite_score": 5.375
    },
    {
      "symbol": "NG=F",
      "display_name": "Natural Gas Futures (NG=F)",
      "asset_class": "commodities",
      "current_spot_pricing": 2.94,
      "twenty_four_hour_absolute_price_variance": 0.0,
      "twenty_four_hour_percentage_price_variance": 0.0,
      "current_institutional_bid_price": 2.935,
      "current_institutional_ask_price": 2.954,
      "daily_opening_price": 3.016,
      "daily_high_price": 3.022,
      "daily_low_price": 2.874,
      "previous_session_close": 2.94,
      "last_updated": "2026-07-12T16:16:26.153485+00:00",
      "calculated_comprehensive_fundamental_bias": "Bullish",
      "final_composite_score": 5.375
    },
    {
      "symbol": "HG=F",
      "display_name": "Copper Futures (HG=F)",
      "asset_class": "commodities",
      "current_spot_pricing": 6.282,
      "twenty_four_hour_absolute_price_variance": 0.0,
      "twenty_four_hour_percentage_price_variance": 0.0,
      "current_institutional_bid_price": 6.25,
      "current_institutional_ask_price": 6.3,
      "daily_opening_price": 6.245,
      "daily_high_price": 6.3255,
      "daily_low_price": 6.2355,
      "previous_session_close": 6.282,
      "last_updated": "2026-07-12T16:16:26.421288+00:00",
      "calculated_comprehensive_fundamental_bias": "Bullish",
      "final_composite_score": 5.375
    },
    {
      "symbol": "PL=F",
      "display_name": "Platinum Futures (PL=F)",
      "asset_class": "commodities",
      "current_spot_pricing": 1629.0,
      "twenty_four_hour_absolute_price_variance": 0.0,
      "twenty_four_hour_percentage_price_variance": 0.0,
      "current_institutional_bid_price": 1635.0,
      "current_institutional_ask_price": 1642.9,
      "daily_opening_price": 1623.300049,
      "daily_high_price": 1652.5,
      "daily_low_price": 1614.400024,
      "previous_session_close": 1629.0,
      "last_updated": "2026-07-12T16:16:26.782729+00:00",
      "calculated_comprehensive_fundamental_bias": "Bullish",
      "final_composite_score": 5.375
    },
    {
      "symbol": "PA=F",
      "display_name": "Palladium Futures (PA=F)",
      "asset_class": "commodities",
      "current_spot_pricing": 1276.300049,
      "twenty_four_hour_absolute_price_variance": 0.0,
      "twenty_four_hour_percentage_price_variance": 0.0,
      "current_institutional_bid_price": 1266.5,
      "current_institutional_ask_price": 1286.0,
      "daily_opening_price": 1252.5,
      "daily_high_price": 1289.0,
      "daily_low_price": 1250.5,
      "previous_session_close": 1276.300049,
      "last_updated": "2026-07-12T16:16:27.137886+00:00",
      "calculated_comprehensive_fundamental_bias": "Bullish",
      "final_composite_score": 5.375
    },
    {
      "symbol": "ZC=F",
      "display_name": "Corn Futures (ZC=F)",
      "asset_class": "commodities",
      "current_spot_pricing": 461.0,
      "twenty_four_hour_absolute_price_variance": 0.0,
      "twenty_four_hour_percentage_price_variance": 0.0,
      "current_institutional_bid_price": 460.0,
      "current_institutional_ask_price": 460.0,
      "daily_opening_price": 451.0,
      "daily_high_price": 462.0,
      "daily_low_price": 447.5,
      "previous_session_close": 461.0,
      "last_updated": "2026-07-12T16:16:27.471284+00:00",
      "calculated_comprehensive_fundamental_bias": "Bullish",
      "final_composite_score": 5.375
    },
    {
      "symbol": "ZW=F",
      "display_name": "Wheat Futures (ZW=F)",
      "asset_class": "commodities",
      "current_spot_pricing": 640.25,
      "twenty_four_hour_absolute_price_variance": 0.0,
      "twenty_four_hour_percentage_price_variance": 0.0,
      "current_institutional_bid_price": 639.0,
      "current_institutional_ask_price": 639.0,
      "daily_opening_price": 618.75,
      "daily_high_price": 649.25,
      "daily_low_price": 614.0,
      "previous_session_close": 640.25,
      "last_updated": "2026-07-12T16:16:27.773646+00:00",
      "calculated_comprehensive_fundamental_bias": "Bullish",
      "final_composite_score": 5.375
    },
    {
      "symbol": "ZS=F",
      "display_name": "Soybean Futures (ZS=F)",
      "asset_class": "commodities",
      "current_spot_pricing": 1190.75,
      "twenty_four_hour_absolute_price_variance": 0.0,
      "twenty_four_hour_percentage_price_variance": 0.0,
      "current_institutional_bid_price": 1186.0,
      "current_institutional_ask_price": 1186.0,
      "daily_opening_price": 1182.5,
      "daily_high_price": 1199.0,
      "daily_low_price": 1172.75,
      "previous_session_close": 1190.75,
      "last_updated": "2026-07-12T16:16:30.020995+00:00",
      "calculated_comprehensive_fundamental_bias": "Bullish",
      "final_composite_score": 5.375
    },
    {
      "symbol": "KC=F",
      "display_name": "Coffee C Futures (KC=F)",
      "asset_class": "commodities",
      "current_spot_pricing": 318.600006,
      "twenty_four_hour_absolute_price_variance": 0.0,
      "twenty_four_hour_percentage_price_variance": 0.0,
      "current_institutional_bid_price": 337.55,
      "current_institutional_ask_price": 337.8,
      "daily_opening_price": 321.0,
      "daily_high_price": 340.700012,
      "daily_low_price": 318.600006,
      "previous_session_close": 318.600006,
      "last_updated": "2026-07-12T16:16:30.474408+00:00",
      "calculated_comprehensive_fundamental_bias": "Bullish",
      "final_composite_score": 5.375
    },
    {
      "symbol": "CT=F",
      "display_name": "Cotton Futures (CT=F)",
      "asset_class": "commodities",
      "current_spot_pricing": 79.919998,
      "twenty_four_hour_absolute_price_variance": 0.0,
      "twenty_four_hour_percentage_price_variance": 0.0,
      "current_institutional_bid_price": 80.14,
      "current_institutional_ask_price": 79.73,
      "daily_opening_price": 79.239998,
      "daily_high_price": 79.669998,
      "daily_low_price": 78.68,
      "previous_session_close": 79.919998,
      "last_updated": "2026-07-12T16:16:30.748682+00:00",
      "calculated_comprehensive_fundamental_bias": "Bullish",
      "final_composite_score": 5.375
    },
    {
      "symbol": "SB=F",
      "display_name": "Sugar Futures (SB=F)",
      "asset_class": "commodities",
      "current_spot_pricing": 14.86,
      "twenty_four_hour_absolute_price_variance": 0.0,
      "twenty_four_hour_percentage_price_variance": 0.0,
      "current_institutional_bid_price": 14.86,
      "current_institutional_ask_price": 14.87,
      "daily_opening_price": 15.14,
      "daily_high_price": 15.14,
      "daily_low_price": 14.71,
      "previous_session_close": 14.86,
      "last_updated": "2026-07-12T16:16:30.953743+00:00",
      "calculated_comprehensive_fundamental_bias": "Bullish",
      "final_composite_score": 5.375
    },
    {
      "symbol": "CC=F",
      "display_name": "Cocoa Futures (CC=F)",
      "asset_class": "commodities",
      "current_spot_pricing": 6100.0,
      "twenty_four_hour_absolute_price_variance": 0.0,
      "twenty_four_hour_percentage_price_variance": 0.0,
      "current_institutional_bid_price": 5971.0,
      "current_institutional_ask_price": 5972.0,
      "daily_opening_price": 6363.0,
      "daily_high_price": 6310.0,
      "daily_low_price": 5777.0,
      "previous_session_close": 6100.0,
      "last_updated": "2026-07-12T16:16:31.349975+00:00",
      "calculated_comprehensive_fundamental_bias": "Bullish",
      "final_composite_score": 5.375
    },
    {
      "symbol": "BTC-USD",
      "display_name": "Bitcoin / United States Dollar (BTC-USD)",
      "asset_class": "crypto",
      "current_spot_pricing": 64064.441406,
      "twenty_four_hour_absolute_price_variance": 262.414062,
      "twenty_four_hour_percentage_price_variance": 0.4113,
      "current_institutional_bid_price": 63777.508,
      "current_institutional_ask_price": 63777.508,
      "daily_opening_price": 63777.507812,
      "daily_high_price": 64189.339844,
      "daily_low_price": 63630.296875,
      "previous_session_close": 63802.027344,
      "last_updated": "2026-07-12T16:16:31.659974+00:00",
      "calculated_comprehensive_fundamental_bias": "Bullish",
      "final_composite_score": 5.1
    },
    {
      "symbol": "ETH-USD",
      "display_name": "Ethereum / United States Dollar (ETH-USD)",
      "asset_class": "crypto",
      "current_spot_pricing": 1818.699951,
      "twenty_four_hour_absolute_price_variance": 30.600342,
      "twenty_four_hour_percentage_price_variance": 1.7113,
      "current_institutional_bid_price": 1786.8636,
      "current_institutional_ask_price": 1786.8636,
      "daily_opening_price": 1786.863647,
      "daily_high_price": 1824.489746,
      "daily_low_price": 1782.504395,
      "previous_session_close": 1788.099609,
      "last_updated": "2026-07-12T16:16:31.937073+00:00",
      "calculated_comprehensive_fundamental_bias": "Bullish",
      "final_composite_score": 5.1
    },
    {
      "symbol": "SOL-USD",
      "display_name": "Solana / United States Dollar (SOL-USD)",
      "asset_class": "crypto",
      "current_spot_pricing": 77.419998,
      "twenty_four_hour_absolute_price_variance": 0.595833,
      "twenty_four_hour_percentage_price_variance": 0.7756,
      "current_institutional_bid_price": 76.81236,
      "current_institutional_ask_price": 76.81236,
      "daily_opening_price": 76.812363,
      "daily_high_price": 77.566475,
      "daily_low_price": 75.879219,
      "previous_session_close": 76.824165,
      "last_updated": "2026-07-12T16:16:32.258576+00:00",
      "calculated_comprehensive_fundamental_bias": "Bullish",
      "final_composite_score": 5.1
    },
    {
      "symbol": "BNB-USD",
      "display_name": "BNB / United States Dollar (BNB-USD)",
      "asset_class": "crypto",
      "current_spot_pricing": 581.140015,
      "twenty_four_hour_absolute_price_variance": 6.250549,
      "twenty_four_hour_percentage_price_variance": 1.0873,
      "current_institutional_bid_price": 574.83215,
      "current_institutional_ask_price": 574.83215,
      "daily_opening_price": 574.832153,
      "daily_high_price": 582.730652,
      "daily_low_price": 570.320984,
      "previous_session_close": 574.889465,
      "last_updated": "2026-07-12T16:16:32.548070+00:00",
      "calculated_comprehensive_fundamental_bias": "Bullish",
      "final_composite_score": 5.1
    },
    {
      "symbol": "XRP-USD",
      "display_name": "XRP / United States Dollar (XRP-USD)",
      "asset_class": "crypto",
      "current_spot_pricing": 1.1004,
      "twenty_four_hour_absolute_price_variance": 0.002819,
      "twenty_four_hour_percentage_price_variance": 0.2568,
      "current_institutional_bid_price": 1.097515,
      "current_institutional_ask_price": 1.097515,
      "daily_opening_price": 1.097515,
      "daily_high_price": 1.102118,
      "daily_low_price": 1.0877,
      "previous_session_close": 1.097581,
      "last_updated": "2026-07-12T16:16:33.090855+00:00",
      "calculated_comprehensive_fundamental_bias": "Bullish",
      "final_composite_score": 5.1
    },
    {
      "symbol": "ADA-USD",
      "display_name": "Cardano / United States Dollar (ADA-USD)",
      "asset_class": "crypto",
      "current_spot_pricing": 0.1643,
      "twenty_four_hour_absolute_price_variance": -0.001667,
      "twenty_four_hour_percentage_price_variance": -1.0044,
      "current_institutional_bid_price": 0.165951,
      "current_institutional_ask_price": 0.165951,
      "daily_opening_price": 0.165951,
      "daily_high_price": 0.166205,
      "daily_low_price": 0.162638,
      "previous_session_close": 0.165967,
      "last_updated": "2026-07-12T16:16:33.483625+00:00",
      "calculated_comprehensive_fundamental_bias": "Bullish",
      "final_composite_score": 5.1
    },
    {
      "symbol": "DOGE-USD",
      "display_name": "Dogecoin / United States Dollar (DOGE-USD)",
      "asset_class": "crypto",
      "current_spot_pricing": 0.07354,
      "twenty_four_hour_absolute_price_variance": 0.000271,
      "twenty_four_hour_percentage_price_variance": 0.3699,
      "current_institutional_bid_price": 0.073262,
      "current_institutional_ask_price": 0.073262,
      "daily_opening_price": 0.073262,
      "daily_high_price": 0.073756,
      "daily_low_price": 0.072426,
      "previous_session_close": 0.073269,
      "last_updated": "2026-07-12T16:16:33.742072+00:00",
      "calculated_comprehensive_fundamental_bias": "Bullish",
      "final_composite_score": 5.1
    },
    {
      "symbol": "DOT-USD",
      "display_name": "Polkadot / United States Dollar (DOT-USD)",
      "asset_class": "crypto",
      "current_spot_pricing": 0.843,
      "twenty_four_hour_absolute_price_variance": -0.011136,
      "twenty_four_hour_percentage_price_variance": -1.3038,
      "current_institutional_bid_price": 0.854054,
      "current_institutional_ask_price": 0.854054,
      "daily_opening_price": 0.854054,
      "daily_high_price": 0.857999,
      "daily_low_price": 0.839975,
      "previous_session_close": 0.854136,
      "last_updated": "2026-07-12T16:16:33.996544+00:00",
      "calculated_comprehensive_fundamental_bias": "Bullish",
      "final_composite_score": 5.1
    },
    {
      "symbol": "AVAX-USD",
      "display_name": "Avalanche / United States Dollar (AVAX-USD)",
      "asset_class": "crypto",
      "current_spot_pricing": 6.39,
      "twenty_four_hour_absolute_price_variance": -0.162605,
      "twenty_four_hour_percentage_price_variance": -2.4815,
      "current_institutional_bid_price": 6.552614,
      "current_institutional_ask_price": 6.552614,
      "daily_opening_price": 6.552614,
      "daily_high_price": 6.552614,
      "daily_low_price": 6.308197,
      "previous_session_close": 6.552605,
      "last_updated": "2026-07-12T16:16:34.310410+00:00",
      "calculated_comprehensive_fundamental_bias": "Bullish",
      "final_composite_score": 5.1
    },
    {
      "symbol": "LINK-USD",
      "display_name": "Chainlink / United States Dollar (LINK-USD)",
      "asset_class": "crypto",
      "current_spot_pricing": 8.051,
      "twenty_four_hour_absolute_price_variance": 0.127113,
      "twenty_four_hour_percentage_price_variance": 1.6042,
      "current_institutional_bid_price": 7.922768,
      "current_institutional_ask_price": 7.922768,
      "daily_opening_price": 7.922768,
      "daily_high_price": 8.079465,
      "daily_low_price": 7.878362,
      "previous_session_close": 7.923887,
      "last_updated": "2026-07-12T16:16:37.094447+00:00",
      "calculated_comprehensive_fundamental_bias": "Bullish",
      "final_composite_score": 5.1
    },
    {
      "symbol": "ATOM-USD",
      "display_name": "Cosmos / United States Dollar (ATOM-USD)",
      "asset_class": "crypto",
      "current_spot_pricing": 1.585,
      "twenty_four_hour_absolute_price_variance": 0.004335,
      "twenty_four_hour_percentage_price_variance": 0.2743,
      "current_institutional_bid_price": 1.580674,
      "current_institutional_ask_price": 1.580674,
      "daily_opening_price": 1.580674,
      "daily_high_price": 1.587148,
      "daily_low_price": 1.557791,
      "previous_session_close": 1.580665,
      "last_updated": "2026-07-12T16:16:37.970661+00:00",
      "calculated_comprehensive_fundamental_bias": "Bullish",
      "final_composite_score": 5.1
    },
    {
      "symbol": "LTC-USD",
      "display_name": "Litecoin / United States Dollar (LTC-USD)",
      "asset_class": "crypto",
      "current_spot_pricing": 44.73,
      "twenty_four_hour_absolute_price_variance": 0.034386,
      "twenty_four_hour_percentage_price_variance": 0.0769,
      "current_institutional_bid_price": 44.686977,
      "current_institutional_ask_price": 44.686977,
      "daily_opening_price": 44.686977,
      "daily_high_price": 44.821758,
      "daily_low_price": 44.381798,
      "previous_session_close": 44.695614,
      "last_updated": "2026-07-12T16:16:38.284346+00:00",
      "calculated_comprehensive_fundamental_bias": "Bullish",
      "final_composite_score": 5.1
    },
    {
      "symbol": "BCH-USD",
      "display_name": "Bitcoin Cash / United States Dollar (BCH-USD)",
      "asset_class": "crypto",
      "current_spot_pricing": 244.419998,
      "twenty_four_hour_absolute_price_variance": 0.013443,
      "twenty_four_hour_percentage_price_variance": 0.0055,
      "current_institutional_bid_price": 244.40387,
      "current_institutional_ask_price": 244.40387,
      "daily_opening_price": 244.40387,
      "daily_high_price": 247.177383,
      "daily_low_price": 243.378998,
      "previous_session_close": 244.406555,
      "last_updated": "2026-07-12T16:16:38.807728+00:00",
      "calculated_comprehensive_fundamental_bias": "Bullish",
      "final_composite_score": 5.1
    }
  ]
}